README.md
setup.py
nickname/Name.py
nickname/__init__.py
nickname/example.py
nickname/test.py
nickname.egg-info/PKG-INFO
nickname.egg-info/SOURCES.txt
nickname.egg-info/dependency_links.txt
nickname.egg-info/top_level.txt