Metadata-Version: 2.1
Name: nickname
Version: 0.0.0.7
Summary: Name matching.
Home-page: https://github.com/Tsangares/nickname
Author-email: william.wyatt@cgu.edu
License: UNKNOWN
Platform: UNKNOWN
Classifier: Programming Language :: Python :: 3
Classifier: License :: OSI Approved :: MIT License
Classifier: Operating System :: OS Independent
Requires-Python: >=3.6
